Workbook

Sheet E.General
B2: Modelo Generico Presupuesto para la ejecución del Proyecto de Investigación
B4: Ítem | C4: Valor en Pesos Colombianos ( $) | D4: Fuente de Financiamiento* | G4: Total ($)
D5: Fuente A | E5: Fuente B | F5: Recursos propios
B6: A. Personal
B7: Docente Investigador | C7: =+'A-Personal'!F7 -> 0 | D7: =+C7*0% -> 0 | E7: =+C7*40% -> 0 | F7: =+C7*20% -> 0 | G7: =+D7+E7+F7 -> 0
B8: Universitario | C8: =+'A-Personal'!F8 -> 3000000 | D8: =+C8*0% -> 0 | E8: =+C8*0% -> 0 | F8: =+C8*100% -> 3000000 | G8: =+D8+E8+F8 -> 3000000
B9: Asistente | C9: =+'A-Personal'!F9 -> 0 | D9: =+C9*0% -> 0 | E9: =+C9*0% -> 0 | F9: =+C9*100% -> 0 | G9: =+D9+E9+F9 -> 0
B10: Apoyo Administrativo | C10: =+'A-Personal'!F10 -> 0 | D10: =+C10*0% -> 0 | E10: =+C10*0% -> 0 | F10: =+C10*100% -> 0 | G10: =+D10+E10+F10 -> 0
B11: =+'A-Personal'!B11 -> Subtotal | D11: =+C11*0% -> 0 | E11: =+C11*0% -> 0 | F11: =+C11*100% -> 0
B12: Subtotal | C12: =+'A-Personal'!F11 -> 3000000 | D12: =+C12*0% -> 0 | E12: =+C12*0% -> 0 | F12: =+C12*100% -> 3000000 | G12: =SUM(G7:G10) -> 3000000
B13: B. Equipos y Software | D13: =+C13*0% -> 0 | E13: =+C13*0% -> 0 | F13: =+C13*100% -> 0
B14: =+'B-Equipos'!B6 -> Computadores | C14: =+'B-Equipos'!F6 -> 7500000 | D14: =+C14*0% -> 0 | E14: =+C14*0% -> 0 | F14: =+C14*100% -> 7500000 | G14: =+F14+E14+D14 -> 7500000
B15: =+'B-Equipos'!B7 -> Impresoras | C15: =+'B-Equipos'!F7 -> 1000000 | D15: =+C15*0% -> 0 | E15: =+C15*0% -> 0 | F15: =+C15*100% -> 1000000 | G15: =+F15+E15+D15 -> 1000000
B16: =+'B-Equipos'!B8 -> Paquete de Office | C16: =+'B-Equipos'!F8 -> 450000 | D16: =+C16*0% -> 0 | E16: =+C16*0% -> 0 | F16: =+C16*100% -> 450000 | G16: =+F16+E16+D16 -> 450000
B17: Subtotal | C17: =+'B-Equipos'!F10 -> 8950000 | D17: =+C17*0% -> 0 | E17: =+C17*0% -> 0 | F17: =+C17*100% -> 8950000 | G17: =SUM(G14:G16) -> 8950000
B18: C. Viajes y Salidas de Campo | D18: =+C18*0% -> 0 | E18: =+C18*0% -> 0 | F18: =+C18*100% -> 0
B19: Gasolina | C19: =+'C-Viajes'!F6 -> 60000 | D19: =+C19*0% -> 0 | E19: =+C19*0% -> 0 | F19: =+C19*100% -> 60000 | G19: =+D19+E19+F19 -> 60000
B20: Peajes | C20: =+'C-Viajes'!F7 -> 0 | D20: =+C20*0% -> 0 | E20: =+C20*0% -> 0 | F20: =+C20*100% -> 0 | G20: =+D20+E20+F20 -> 0
B21: Subtotal | C21: =+'C-Viajes'!F9 -> 60000 | D21: =+C21*0% -> 0 | E21: =+C21*0% -> 0 | F21: =+C21*100% -> 60000 | G21: =SUM(G19:G20) -> 60000
B22: D. Materiales | D22: =+C22*0% -> 0 | E22: =+C22*0% -> 0 | F22: =+C22*100% -> 0
B23: Publicacion Revistas | C23: =+'D-Materiales'!F7 -> 0 | D23: =+C23*0% -> 0 | E23: =+C23*0% -> 0 | F23: =+C23*100% -> 0 | G23: =+D23+E23+F23 -> 0
B24: Papeleria | C24: =+'D-Materiales'!F8 -> 0 | D24: =+C24*0% -> 0 | E24: =+C24*0% -> 0 | F24: =+C24*100% -> 0 | G24: =+D24+E24+F24 -> 0
B25: USB, DVD | C25: 0 | D25: =+C25*0% -> 0 | E25: =+C25*0% -> 0 | F25: =+C25*100% -> 0 | G25: =+D25+E25+F25 -> 0
B26: Subtotal | C26: =+'D-Materiales'!F11 -> 0 | D26: =+C26*0% -> 0 | E26: =+C26*0% -> 0 | F26: =+C26*100% -> 0 | G26: =SUM(G23:G25) -> 0
B27: E. Asesorías técnicas y de soporte | D27: =+C27*0% -> 0 | E27: =+C27*0% -> 0 | F27: =+C27*100% -> 0
B28: Asesoría especializada | C28: =+'E-Ase Tecn. y Soporte'!F7 -> 0 | D28: =+C28*0% -> 0 | E28: =+C28*0% -> 0 | F28: =+C28*100% -> 0 | G28: =+D28+E28+F28 -> 0
B29: Suscripción Revista | C29: =+'E-Ase Tecn. y Soporte'!F8 -> 0 | D29: =+C29*0% -> 0 | E29: =+C29*0% -> 0 | F29: =+C29*100% -> 0 | G29: =+D29+E29+F29 -> 0
B30: Subtotal | C30: =+'E-Ase Tecn. y Soporte'!F10 -> 0 | D30: =+C30*0% -> 0 | E30: =+C30*0% -> 0 | F30: =+C30*100% -> 0 | G30: =SUM(G28:G29) -> 0
B31: E. Otros
B32: Mantenimiento | C32: =+'F-Otros'!F7 -> 0 | D32: =+C32*0% -> 0 | E32: =+C32*0% -> 0 | F32: =+C32*100% -> 0 | G32: =+D32+E32+F32 -> 0
B33: S. Públicos | C33: =+'F-Otros'!F8 -> 0 | D33: =+C33*0% -> 0 | E33: =+C33*0% -> 0 | F33: =+C33*100% -> 0 | G33: =+D33+E33+F33 -> 0
B34: Seguros | C34: =+'F-Otros'!F9 -> 0 | D34: =+C34*0% -> 0 | E34: =+C34*0% -> 0 | F34: =+C34*100% -> 0 | G34: =+D34+E34+F34 -> 0
B35: Tasas de inmpuestos | C35: =+'F-Otros'!F10 -> 0 | D35: =+C35*0% -> 0 | E35: =+C35*0% -> 0 | F35: =+C35*100% -> 0 | G35: =+D35+E35+F35 -> 0
B36: Alimentacion | C36: =+'F-Otros'!F11 -> 210000 | D36: =+C36*0% -> 0 | E36: =+C36*0% -> 0 | F36: =+C36*100% -> 210000 | G36: =+D36+E36+F36 -> 210000
B37: Subtotal | C37: =+'F-Otros'!F12 -> 210000 | D37: =+C37*0% -> 0 | E37: =+C37*0% -> 0 | F37: =+C37*100% -> 210000 | G37: =SUM(G32:G36) -> 210000
B38: Total | C38: =+C12+C17+C21+C26+C30+C37 -> 12220000 | D38: =+C38*0% -> 0 | E38: =+C38*0% -> 0 | F38: =+C38*100% -> 12220000 | G38: =+G12+G17+G21+G26+G30+G37 -> 12220000
B39: Porcentaje | C39: 1 | D39: =+C39*0% -> 0 | E39: =+C39*0% -> 0 | F39: =+C39*100% -> 1 | G39: =+F39+E39+D39 -> 1
B40: *Rubros No Financiables con fuentes externas | D40: =+C40*0% -> 0 | E40: =+C40*0% -> 0 | F40: =+C40*100% -> 0

Sheet A-Personal
B3: Personal requerido para la ejecución del proyecto.
B5: Categoría | C5: Salario - Honorario - Mensual ($) | D5: Cantidad | E5: Tiempo de Vinculación en meses | F5: Importe $
B7: Docente Investigador | C7: 0 | D7: 0 | E7: 0 | F7: =+C7*D7*E7 -> 0
B8: Universitario | C8: 1000000 | D8: 3 | E8: 1 | F8: =+C8*D8*E8 -> 3000000
B9: Apoyo Administrativo | C9: 0 | D9: 0 | E9: 0 | F9: =+E9*D9*C9 -> 0
F10: =+E10*D10*C10 -> 0
B11: Subtotal | F11: =SUM(F7:F10) -> 3000000

Sheet B-Equipos
B2: Equipos y software
B4: Descripción | C4: Unidad de Medida | D4: Cantidad | E4: Precio Unitario ($) | F4: Importe $
B6: Computadores | C6: Unidad | D6: 3 | E6: 2500000 | F6: =+D6*E6 -> 7500000
B7: Impresoras | C7: Unidad | D7: 1 | E7: 1000000 | F7: =+D7*E7 -> 1000000
B8: Paquete de Office | C8: Unidad | D8: 3 | E8: 150000 | F8: =+D8*E8 -> 450000
F9: =+D9*E9 -> 0
B10: Subtotal | F10: =SUM(F6:F9) -> 8950000

Sheet C-Viajes
B3: Viajes y salidas de Campo
B5: Concepto | C5: Tarifa diaria en $ | D5: Numero de días por viaje/salida de campo | E5: Número de Viajes y/o salidas de campo | F5: Importe ($)
B6: Gasolina | C6: 20000 | D6: 1 | E6: 3 | F6: =+E6*D6*C6 -> 60000
B7: Peajes | C7: 0 | E7: 0 | F7: =+C7*E7 -> 0
F8: =+E8*D8*C8 -> 0
B9: Subtotal | F9: =SUM(F6:F8) -> 60000

Sheet D-Materiales
B3: Materiales
B5: Descripción del Material | C5: Unidad de medida | D5: Cantidad | E5: Precio Unitario ($) | F5: Importe $
B7: Publicacion Revistas | C7: Unidad | D7: 0 | E7: 0 | F7: =+E7*D7 -> 0
B8: Papeleria-Rexma | C8: Unidad | D8: 0 | E8: 0 | F8: =+E8*D8 -> 0
B9: usb | C9: Unidad | D9: 0 | E9: 0 | F9: =+E9*D9 -> 0
B10: DVD | C10: Unidad | D10: 0 | E10: 0 | F10: =+E10*D10 -> 0
B11: Subtotal | F11: =SUM(F7:F10) -> 0

Sheet E-Ase Tecn. y Soporte
B3: Asesorías técnicas y soporte
B5: Descripción | C5: Unidad de medida | D5: Cantidad | E5: Precio Unitario ($) | F5: Importe $
B7: Asesoría especializada | C7: H/H | D7: 0 | E7: 0 | F7: =+E7*D7 -> 0
B8: Suscripción Revista | C8: Unidad | D8: 0 | F8: =+E8*D8 -> 0
F9: =+E9*D9 -> 0
B10: Subtotal | F10: =SUM(F7:F9) -> 0

Sheet F-Otros
B3: Otros
B5: Descripción | C5: Unidad de medida | D5: Cantidad | E5: Precio Unitario ($) | F5: Importe $
B7: Mantenimiento | F7: =+E7*D7 -> 0
B8: S. Públicos | F8: =+E8*D8 -> 0
B9: Garantias | F9: =+E9*D9 -> 0
B10: Tasas Impuestos | F10: =+E10*D10 -> 0
B11: Alimentacion | D11: 3 | E11: 70000 | F11: =+E11*D11 -> 210000
B12: Subtotal | F12: =SUM(F7:F11) -> 210000

Sheet Fujo de Caja
B2: Modelo de Flujo de Caja para la Ejecucion del proyecto * Componente egresos
B4: Actividades/Tareas/ subtareas** | E4: Fuentes de Financiamiento | H4: Requerimiento de recuros ($)
E5: Fuente A | F5: Fuente B | G5: Recursos propios | H5: Mes 1 | I5: Mes 2 | J5: Mes 3 | K5: Mes 4 | L5: Mes 5 | M5: Mes 6 | N5: Mes 7 | O5: Mes 8 | P5: Mes 9 | Q5: Mes 10 | R5: Mes n-1 | S5: Mes n | T5: Total
B6: Actividad A
C7: Tarea No 1
D8: Subtarea __ | T8: =SUM(H8:S8) -> 0
D9: Subtarea __ | T9: =SUM(H9:S9) -> 0
C10: Tarea No 2
D11: Subtarea __ | T11: =SUM(H11:S11) -> 0
D12: Subtarea __ | T12: =SUM(H12:S12) -> 0
B13: Actividad B
C14: Tarea No 3
D15: Subtarea __ | T15: =SUM(H15:S15) -> 0
D16: Subtarea __ | T16: =SUM(H16:S16) -> 0
C17: Tarea No 4
D18: Subtarea __ | T18: =SUM(H18:S18) -> 0
D19: Subtarea __ | T19: =SUM(H19:S19) -> 0
B23: Subtotales | E23: =SUM(E6:E22) -> 0 | F23: =SUM(F6:F22) -> 0 | G23: =SUM(G6:G22) -> 0
B24: Costo total del proyecto. | T24: =SUM(T6:T23) -> 0
B25: * Horizonte de ejecución del proyecto.

Sheet Hoja2
